society/__init__.py
society/__main__.py
society/agent_util.py
society/characters.py
society/chat_client.py
society/cli.py
society/data.py
society/datatypes.py
society/deps.py
society/instructions.py
society/runner.py
society/tools.py
society/web/api.py
society/web/frontend/.gitignore
society/web/frontend/eslint.config.js
society/web/frontend/index.html
society/web/frontend/package-lock.json
society/web/frontend/package.json
society/web/frontend/tsconfig.app.json
society/web/frontend/tsconfig.json
society/web/frontend/tsconfig.node.json
society/web/frontend/vite.config.ts
society/web/frontend/src/App.css
society/web/frontend/src/App.tsx
society/web/frontend/src/api.ts
society/web/frontend/src/generated-types.ts
society/web/frontend/src/index.css
society/web/frontend/src/main.tsx
society/web/frontend/src/types.ts
society/web/frontend/src/components/ApiKeyModal.tsx
society/web/frontend/src/components/EmptyState.tsx
society/web/frontend/src/components/Header.tsx
society/web/frontend/src/components/LoadingState.tsx
society/web/frontend/src/components/NewRunForm.tsx
society/web/frontend/src/components/index.ts
society/web/frontend/src/components/characters/CharacterDetailView.tsx
society/web/frontend/src/components/characters/CharacterList.tsx
society/web/frontend/src/components/characters/NewCharacterForm.tsx
society/web/frontend/src/components/home/HomeScreen.tsx
society/web/frontend/src/components/home/RunsList.tsx
society/web/frontend/src/components/simulation/ContentView.tsx
society/web/frontend/src/components/simulation/EventsView.tsx
society/web/frontend/src/components/simulation/FinalResult.tsx
society/web/frontend/src/components/simulation/MessagesView.tsx
society/web/frontend/src/components/simulation/PersonCard.tsx
society/web/frontend/src/components/simulation/Sidebar.tsx
society/web/frontend/src/components/simulation/SimulationView.tsx
society/web/scripts/gen_types.py
society-0.1.2.dist-info/METADATA
society-0.1.2.dist-info/WHEEL
society-0.1.2.dist-info/entry_points.txt
society-0.1.2.dist-info/licenses/LICENSE
society-0.1.2.dist-info/RECORD
